autoflows/__init__.py
autoflows/autoflow.py
autoflows-0.0.1.data/data/LICENSE
autoflows-0.0.1.dist-info/LICENSE
autoflows-0.0.1.dist-info/METADATA
autoflows-0.0.1.dist-info/WHEEL
autoflows-0.0.1.dist-info/top_level.txt
autoflows-0.0.1.dist-info/RECORD
