Metadata-Version: 2.1
Name: autoflows
Version: 0.0.1
Summary: Automated Flyte workflows, powered by GPTs.
Home-page: https://github.com/unionai-oss/autoflows/
Author: unionai-oss
Author-email: info@union.ai
License: Apache
Project-URL: Source Code, https://github.com/unionai-oss/autoflows/
Project-URL: Issue Tracker, https://github.com/unionai-oss/autoflows/issues
Keywords: machine-learning,artificial-intelligence,orchestration
Platform: any
Classifier: Development Status :: 4 - Beta
Classifier: Operating System :: OS Independent
Classifier: License :: OSI Approved :: Apache Software License
Classifier: Intended Audience :: Science/Research
Classifier: Intended Audience :: Developers
Classifier: Programming Language :: Python
Classifier: Programming Language :: Python :: 3
Classifier: Programming Language :: Python :: 3.8
Classifier: Programming Language :: Python :: 3.9
Classifier: Programming Language :: Python :: 3.10
Classifier: Programming Language :: Python :: 3.11
Classifier: Topic :: Scientific/Engineering :: Artificial Intelligence
Classifier: Topic :: Software Development :: Libraries :: Application Frameworks
Requires-Python: >3.7
License-File: LICENSE
Requires-Dist: docstring-parser
Requires-Dist: flytekit
Requires-Dist: openai
